hscitorchutil/dataset.py
hscitorchutil/processlocal.py
hscitorchutil/sqlite.py
hscitorchutil-0.3.1.dist-info/METADATA
hscitorchutil-0.3.1.dist-info/WHEEL
hscitorchutil-0.3.1.dist-info/RECORD
